srng
